MANIFEST.in
README.md
setup.py
tigermcp/__init__.py
tigermcp/server.py
tigermcp/version.py
tigermcp.egg-info/PKG-INFO
tigermcp.egg-info/SOURCES.txt
tigermcp.egg-info/dependency_links.txt
tigermcp.egg-info/entry_points.txt
tigermcp.egg-info/requires.txt
tigermcp.egg-info/top_level.txt
tigermcp/__pycache__/__init__.cpython-311.pyc
tigermcp/__pycache__/server.cpython-311.pyc
tigermcp/__pycache__/version.cpython-311.pyc