Metadata-Version: 2.4
Name: tigermcp
Version: 0.1.3
Summary: Tiger Broker API MCP Server
Home-page: https://github.com/tigerfintech/openapi-python-sdk
Author: TigerBrokers
Author-email: openapi@itiger.com
License: Apache License v2
Classifier: Programming Language :: Python :: 3
Classifier: Operating System :: OS Independent
Requires-Python: >=3.9
Requires-Dist: tigeropen>=3.4.6
Requires-Dist: mcp[cli]>=1.13.0
Dynamic: author
Dynamic: author-email
Dynamic: classifier
Dynamic: description
Dynamic: description-content-type
Dynamic: home-page
Dynamic: license
Dynamic: requires-dist
Dynamic: requires-python
Dynamic: summary
